wpapijwt/__init__.py
wpapijwt/wp_api.py
wpapijwt/resources/__init__.py
wpapijwt/resources/functions.py
wordpress_api_jwt-0.0.9.dist-info/LICENSE
wordpress_api_jwt-0.0.9.dist-info/METADATA
wordpress_api_jwt-0.0.9.dist-info/WHEEL
wordpress_api_jwt-0.0.9.dist-info/top_level.txt
wordpress_api_jwt-0.0.9.dist-info/RECORD
