Metadata-Version: 2.1
Name: wordpress-api-jwt
Version: 0.0.9
Summary: A very simple package to make API calls easily with WordPress using JWT Authentication
Home-page: https://github.com/aleaforny/python-wordpress-api-jwt
Author: Baptiste VANDENBORGHT
Author-email: baptiste@twiiky-corp.fr
License: UNKNOWN
Project-URL: Bug Tracker, https://github.com/aleaforny/python-wordpress-api-jwt/issues
Platform: UNKNOWN
Classifier: Programming Language :: Python :: 3
Classifier: License :: OSI Approved :: MIT License
Classifier: Operating System :: OS Independent
Requires-Python: >=3.6
License-File: LICENSE
Requires-Dist: requests
